{
    "sourceFile": "package.json",
    "activeCommit": 0,
    "commits": [
        {
            "activePatchIndex": 60,
            "patches": [
                {
                    "date": 1776584800003,
                    "content": "Index: \n===================================================================\n--- \n+++ \n"
                },
                {
                    "date": 1776587161757,
                    "content": "Index: \n===================================================================\n--- \n+++ \n@@ -1,9 +1,9 @@\n {\n   \"name\": \"intellij-styled-search\",\n   \"displayName\": \"IntelliJ Styled Search\",\n   \"description\": \"IntelliJ IDEA style project search — peek-like movable panel with workspace file results\",\n-  \"version\": \"0.0.2\",\n+  \"version\": \"0.0.3\",\n   \"publisher\": \"newdlops\",\n   \"license\": \"MIT\",\n   \"icon\": \"resources/icon.png\",\n   \"repository\": {\n"
                },
                {
                    "date": 1776600140079,
                    "content": "Index: \n===================================================================\n--- \n+++ \n@@ -103,10 +103,10 @@\n           \"description\": \"Maximum file size (bytes) to include in search.\"\n         },\n         \"intellijStyledSearch.maxResults\": {\n           \"type\": \"number\",\n-          \"default\": 2000,\n-          \"description\": \"Maximum number of match lines to return.\"\n+          \"default\": 0,\n+          \"description\": \"Maximum number of match lines to return. Set to 0 or less for unlimited.\"\n         }\n       }\n     }\n   },\n"
                },
                {
                    "date": 1776602064768,
                    "content": "Index: \n===================================================================\n--- \n+++ \n@@ -1,9 +1,9 @@\n {\n   \"name\": \"intellij-styled-search\",\n   \"displayName\": \"IntelliJ Styled Search\",\n   \"description\": \"IntelliJ IDEA style project search — peek-like movable panel with workspace file results\",\n-  \"version\": \"0.0.3\",\n+  \"version\": \"0.0.4\",\n   \"publisher\": \"newdlops\",\n   \"license\": \"MIT\",\n   \"icon\": \"resources/icon.png\",\n   \"repository\": {\n"
                },
                {
                    "date": 1776606473818,
                    "content": "Index: \n===================================================================\n--- \n+++ \n@@ -103,10 +103,10 @@\n           \"description\": \"Maximum file size (bytes) to include in search.\"\n         },\n         \"intellijStyledSearch.maxResults\": {\n           \"type\": \"number\",\n-          \"default\": 0,\n-          \"description\": \"Maximum number of match lines to return. Set to 0 or less for unlimited.\"\n+          \"default\": 50000,\n+          \"description\": \"Maximum number of match lines to return. Values at or below 0 fall back to the built-in safety cap.\"\n         }\n       }\n     }\n   },\n"
                },
                {
                    "date": 1776606479702,
                    "content": "Index: \n===================================================================\n--- \n+++ \n@@ -103,9 +103,9 @@\n           \"description\": \"Maximum file size (bytes) to include in search.\"\n         },\n         \"intellijStyledSearch.maxResults\": {\n           \"type\": \"number\",\n-          \"default\": 50000,\n+          \"default\": 0,\n           \"description\": \"Maximum number of match lines to return. Values at or below 0 fall back to the built-in safety cap.\"\n         }\n       }\n     }\n"
                },
                {
                    "date": 1776607925763,
                    "content": "Index: \n===================================================================\n--- \n+++ \n@@ -1,9 +1,9 @@\n {\n   \"name\": \"intellij-styled-search\",\n   \"displayName\": \"IntelliJ Styled Search\",\n   \"description\": \"IntelliJ IDEA style project search — peek-like movable panel with workspace file results\",\n-  \"version\": \"0.0.4\",\n+  \"version\": \"0.0.5\",\n   \"publisher\": \"newdlops\",\n   \"license\": \"MIT\",\n   \"icon\": \"resources/icon.png\",\n   \"repository\": {\n@@ -103,10 +103,10 @@\n           \"description\": \"Maximum file size (bytes) to include in search.\"\n         },\n         \"intellijStyledSearch.maxResults\": {\n           \"type\": \"number\",\n-          \"default\": 0,\n-          \"description\": \"Maximum number of match lines to return. Values at or below 0 fall back to the built-in safety cap.\"\n+          \"default\": 2000,\n+          \"description\": \"How many match lines to load per batch. Scrolling near the bottom loads the next batch. Values at or below 0 fall back to the built-in default.\"\n         }\n       }\n     }\n   },\n"
                },
                {
                    "date": 1776611026600,
                    "content": "Index: \n===================================================================\n--- \n+++ \n@@ -1,9 +1,9 @@\n {\n   \"name\": \"intellij-styled-search\",\n   \"displayName\": \"IntelliJ Styled Search\",\n   \"description\": \"IntelliJ IDEA style project search — peek-like movable panel with workspace file results\",\n-  \"version\": \"0.0.5\",\n+  \"version\": \"0.0.6\",\n   \"publisher\": \"newdlops\",\n   \"license\": \"MIT\",\n   \"icon\": \"resources/icon.png\",\n   \"repository\": {\n"
                },
                {
                    "date": 1776643672682,
                    "content": "Index: \n===================================================================\n--- \n+++ \n@@ -1,9 +1,9 @@\n {\n   \"name\": \"intellij-styled-search\",\n   \"displayName\": \"IntelliJ Styled Search\",\n   \"description\": \"IntelliJ IDEA style project search — peek-like movable panel with workspace file results\",\n-  \"version\": \"0.0.6\",\n+  \"version\": \"0.0.7\",\n   \"publisher\": \"newdlops\",\n   \"license\": \"MIT\",\n   \"icon\": \"resources/icon.png\",\n   \"repository\": {\n"
                },
                {
                    "date": 1776663631766,
                    "content": "Index: \n===================================================================\n--- \n+++ \n@@ -1,9 +1,9 @@\n {\n   \"name\": \"intellij-styled-search\",\n   \"displayName\": \"IntelliJ Styled Search\",\n   \"description\": \"IntelliJ IDEA style project search — peek-like movable panel with workspace file results\",\n-  \"version\": \"0.0.7\",\n+  \"version\": \"0.0.8\",\n   \"publisher\": \"newdlops\",\n   \"license\": \"MIT\",\n   \"icon\": \"resources/icon.png\",\n   \"repository\": {\n@@ -53,8 +53,18 @@\n         \"title\": \"Rebuild Search Index\",\n         \"category\": \"IntelliJ Search\"\n       },\n       {\n+        \"command\": \"intellijStyledSearch.showZoektInfo\",\n+        \"title\": \"Show Zoekt Diagnostics\",\n+        \"category\": \"IntelliJ Search\"\n+      },\n+      {\n+        \"command\": \"intellijStyledSearch.explainZoektQuery\",\n+        \"title\": \"Explain Query With Zoekt\",\n+        \"category\": \"IntelliJ Search\"\n+      },\n+      {\n         \"command\": \"intellijStyledSearch.diagnoseFileInIndex\",\n         \"title\": \"Diagnose Active File in Search Index\",\n         \"category\": \"IntelliJ Search\"\n       }\n@@ -83,8 +93,17 @@\n     },\n     \"configuration\": {\n       \"title\": \"IntelliJ Styled Search\",\n       \"properties\": {\n+        \"intellijStyledSearch.engine\": {\n+          \"type\": \"string\",\n+          \"enum\": [\n+            \"zoekt\",\n+            \"codesearch\"\n+          ],\n+          \"default\": \"zoekt\",\n+          \"markdownDescription\": \"Search engine to use. `zoekt` runs the Rust local shard/mmap engine with automatic codesearch fallback when the runtime is unavailable or still warming up. `codesearch` uses the existing TypeScript planner plus ripgrep verifier.\"\n+        },\n         \"intellijStyledSearch.excludeGlobs\": {\n           \"type\": \"array\",\n           \"default\": [\n             \"**/node_modules/**\",\n@@ -111,8 +130,9 @@\n     }\n   },\n   \"scripts\": {\n     \"bundle:monaco\": \"node scripts/bundleMonaco.js\",\n+    \"bench:zoekt\": \"node scripts/runZoektBenchmark.js\",\n     \"compile\": \"npm run bundle:monaco && tsc -p ./\",\n     \"watch\": \"tsc -watch -p ./\",\n     \"vscode:prepublish\": \"npm run compile\",\n     \"pretest\": \"npm run compile\",\n"
                },
                {
                    "date": 1776673017147,
                    "content": "Index: \n===================================================================\n--- \n+++ \n@@ -1,9 +1,9 @@\n {\n   \"name\": \"intellij-styled-search\",\n   \"displayName\": \"IntelliJ Styled Search\",\n   \"description\": \"IntelliJ IDEA style project search — peek-like movable panel with workspace file results\",\n-  \"version\": \"0.0.8\",\n+  \"version\": \"0.0.9\",\n   \"publisher\": \"newdlops\",\n   \"license\": \"MIT\",\n   \"icon\": \"resources/icon.png\",\n   \"repository\": {\n@@ -53,8 +53,13 @@\n         \"title\": \"Rebuild Search Index\",\n         \"category\": \"IntelliJ Search\"\n       },\n       {\n+        \"command\": \"intellijStyledSearch.switchEngine\",\n+        \"title\": \"Switch Search Engine\",\n+        \"category\": \"IntelliJ Search\"\n+      },\n+      {\n         \"command\": \"intellijStyledSearch.showZoektInfo\",\n         \"title\": \"Show Zoekt Diagnostics\",\n         \"category\": \"IntelliJ Search\"\n       },\n"
                },
                {
                    "date": 1776740953384,
                    "content": "Index: \n===================================================================\n--- \n+++ \n@@ -1,9 +1,9 @@\n {\n   \"name\": \"intellij-styled-search\",\n   \"displayName\": \"IntelliJ Styled Search\",\n   \"description\": \"IntelliJ IDEA style project search — peek-like movable panel with workspace file results\",\n-  \"version\": \"0.0.9\",\n+  \"version\": \"0.0.91\",\n   \"publisher\": \"newdlops\",\n   \"license\": \"MIT\",\n   \"icon\": \"resources/icon.png\",\n   \"repository\": {\n"
                },
                {
                    "date": 1776740968654,
                    "content": "Index: \n===================================================================\n--- \n+++ \n@@ -1,9 +1,9 @@\n {\n   \"name\": \"intellij-styled-search\",\n   \"displayName\": \"IntelliJ Styled Search\",\n   \"description\": \"IntelliJ IDEA style project search — peek-like movable panel with workspace file results\",\n-  \"version\": \"0.0.91\",\n+  \"version\": \"0.0.10\",\n   \"publisher\": \"newdlops\",\n   \"license\": \"MIT\",\n   \"icon\": \"resources/icon.png\",\n   \"repository\": {\n"
                },
                {
                    "date": 1776783177246,
                    "content": "Index: \n===================================================================\n--- \n+++ \n@@ -1,9 +1,9 @@\n {\n   \"name\": \"intellij-styled-search\",\n   \"displayName\": \"IntelliJ Styled Search\",\n   \"description\": \"IntelliJ IDEA style project search — peek-like movable panel with workspace file results\",\n-  \"version\": \"0.0.10\",\n+  \"version\": \"0.0.11\",\n   \"publisher\": \"newdlops\",\n   \"license\": \"MIT\",\n   \"icon\": \"resources/icon.png\",\n   \"repository\": {\n"
                },
                {
                    "date": 1776823793828,
                    "content": "Index: \n===================================================================\n--- \n+++ \n@@ -1,9 +1,9 @@\n {\n   \"name\": \"intellij-styled-search\",\n   \"displayName\": \"IntelliJ Styled Search\",\n   \"description\": \"IntelliJ IDEA style project search — peek-like movable panel with workspace file results\",\n-  \"version\": \"0.0.11\",\n+  \"version\": \"0.1.1\",\n   \"publisher\": \"newdlops\",\n   \"license\": \"MIT\",\n   \"icon\": \"resources/icon.png\",\n   \"repository\": {\n@@ -129,8 +129,13 @@\n         \"intellijStyledSearch.maxResults\": {\n           \"type\": \"number\",\n           \"default\": 2000,\n           \"description\": \"How many match lines to load per batch. Scrolling near the bottom loads the next batch. Values at or below 0 fall back to the built-in default.\"\n+        },\n+        \"intellijStyledSearch.searchHistoryLimit\": {\n+          \"type\": \"number\",\n+          \"default\": 100,\n+          \"description\": \"Maximum number of executed search queries to keep in the search history dropdown. Set to 0 to disable storing search history.\"\n         }\n       }\n     }\n   },\n"
                },
                {
                    "date": 1776846232164,
                    "content": "Index: \n===================================================================\n--- \n+++ \n@@ -1,9 +1,9 @@\n {\n   \"name\": \"intellij-styled-search\",\n   \"displayName\": \"IntelliJ Styled Search\",\n   \"description\": \"IntelliJ IDEA style project search — peek-like movable panel with workspace file results\",\n-  \"version\": \"0.1.1\",\n+  \"version\": \"0.1.2\",\n   \"publisher\": \"newdlops\",\n   \"license\": \"MIT\",\n   \"icon\": \"resources/icon.png\",\n   \"repository\": {\n"
                },
                {
                    "date": 1776905897621,
                    "content": "Index: \n===================================================================\n--- \n+++ \n@@ -1,9 +1,9 @@\n {\n   \"name\": \"intellij-styled-search\",\n   \"displayName\": \"IntelliJ Styled Search\",\n   \"description\": \"IntelliJ IDEA style project search — peek-like movable panel with workspace file results\",\n-  \"version\": \"0.1.2\",\n+  \"version\": \"0.1.3\",\n   \"publisher\": \"newdlops\",\n   \"license\": \"MIT\",\n   \"icon\": \"resources/icon.png\",\n   \"repository\": {\n"
                },
                {
                    "date": 1776924587095,
                    "content": "Index: \n===================================================================\n--- \n+++ \n@@ -1,9 +1,9 @@\n {\n   \"name\": \"intellij-styled-search\",\n   \"displayName\": \"IntelliJ Styled Search\",\n   \"description\": \"IntelliJ IDEA style project search — peek-like movable panel with workspace file results\",\n-  \"version\": \"0.1.3\",\n+  \"version\": \"0.1.4\",\n   \"publisher\": \"newdlops\",\n   \"license\": \"MIT\",\n   \"icon\": \"resources/icon.png\",\n   \"repository\": {\n"
                },
                {
                    "date": 1777430828169,
                    "content": "Index: \n===================================================================\n--- \n+++ \n@@ -1,9 +1,9 @@\n {\n   \"name\": \"intellij-styled-search\",\n   \"displayName\": \"IntelliJ Styled Search\",\n   \"description\": \"IntelliJ IDEA style project search — peek-like movable panel with workspace file results\",\n-  \"version\": \"0.1.4\",\n+  \"version\": \"0.1.5\",\n   \"publisher\": \"newdlops\",\n   \"license\": \"MIT\",\n   \"icon\": \"resources/icon.png\",\n   \"repository\": {\n"
                },
                {
                    "date": 1777858528566,
                    "content": "Index: \n===================================================================\n--- \n+++ \n@@ -1,9 +1,9 @@\n {\n   \"name\": \"intellij-styled-search\",\n   \"displayName\": \"IntelliJ Styled Search\",\n   \"description\": \"IntelliJ IDEA style project search — peek-like movable panel with workspace file results\",\n-  \"version\": \"0.1.5\",\n+  \"version\": \"0.1.6\",\n   \"publisher\": \"newdlops\",\n   \"license\": \"MIT\",\n   \"icon\": \"resources/icon.png\",\n   \"repository\": {\n@@ -71,8 +71,48 @@\n       {\n         \"command\": \"intellijStyledSearch.diagnoseFileInIndex\",\n         \"title\": \"Diagnose Active File in Search Index\",\n         \"category\": \"IntelliJ Search\"\n+      },\n+      {\n+        \"command\": \"intellijStyledSearch.rebuildCallGraph\",\n+        \"title\": \"Rebuild Call Graph\",\n+        \"category\": \"IntelliJ Search\"\n+      },\n+      {\n+        \"command\": \"intellijStyledSearch.showCallGraphInfo\",\n+        \"title\": \"Show Call Graph Info\",\n+        \"category\": \"IntelliJ Search\"\n+      },\n+      {\n+        \"command\": \"intellijStyledSearch.findCallers\",\n+        \"title\": \"Find Callers\",\n+        \"category\": \"IntelliJ Search\"\n+      },\n+      {\n+        \"command\": \"intellijStyledSearch.findCallees\",\n+        \"title\": \"Find Callees\",\n+        \"category\": \"IntelliJ Search\"\n+      },\n+      {\n+        \"command\": \"intellijStyledSearch.findImplementations\",\n+        \"title\": \"Find Implementations\",\n+        \"category\": \"IntelliJ Search\"\n+      },\n+      {\n+        \"command\": \"intellijStyledSearch.findUsages\",\n+        \"title\": \"Find Usages\",\n+        \"category\": \"IntelliJ Search\"\n+      },\n+      {\n+        \"command\": \"intellijStyledSearch.startMcpServer\",\n+        \"title\": \"Start Call Graph MCP Server\",\n+        \"category\": \"IntelliJ Search\"\n+      },\n+      {\n+        \"command\": \"intellijStyledSearch.stopMcpServer\",\n+        \"title\": \"Stop Call Graph MCP Server\",\n+        \"category\": \"IntelliJ Search\"\n       }\n     ],\n     \"keybindings\": [\n       {\n@@ -86,15 +126,89 @@\n         \"key\": \"ctrl+shift+alt+p\",\n         \"mac\": \"cmd+shift+alt+p\"\n       }\n     ],\n+    \"submenus\": [\n+      {\n+        \"id\": \"intellijStyledSearch.editorContext\",\n+        \"label\": \"IntelliJ Search\"\n+      }\n+    ],\n     \"menus\": {\n       \"editor/context\": [\n         {\n+          \"submenu\": \"intellijStyledSearch.editorContext\",\n+          \"when\": \"editorTextFocus\",\n+          \"group\": \"navigation@98\"\n+        },\n+        {\n           \"command\": \"intellijStyledSearch.searchSelection\",\n           \"when\": \"editorHasSelection\",\n           \"group\": \"navigation@99\"\n         }\n+      ],\n+      \"intellijStyledSearch.editorContext\": [\n+        {\n+          \"command\": \"intellijStyledSearch.searchInProject\",\n+          \"group\": \"1_search@1\"\n+        },\n+        {\n+          \"command\": \"intellijStyledSearch.searchSelection\",\n+          \"when\": \"editorHasSelection\",\n+          \"group\": \"1_search@2\"\n+        },\n+        {\n+          \"command\": \"intellijStyledSearch.findCallees\",\n+          \"group\": \"2_callGraph@2\"\n+        },\n+        {\n+          \"command\": \"intellijStyledSearch.findImplementations\",\n+          \"group\": \"2_callGraph@3\"\n+        },\n+        {\n+          \"command\": \"intellijStyledSearch.findUsages\",\n+          \"group\": \"2_callGraph@4\"\n+        },\n+        {\n+          \"command\": \"intellijStyledSearch.rebuildCallGraph\",\n+          \"group\": \"2_callGraph@5\"\n+        },\n+        {\n+          \"command\": \"intellijStyledSearch.showCallGraphInfo\",\n+          \"group\": \"2_callGraph@6\"\n+        },\n+        {\n+          \"command\": \"intellijStyledSearch.startMcpServer\",\n+          \"group\": \"3_mcp@1\"\n+        },\n+        {\n+          \"command\": \"intellijStyledSearch.stopMcpServer\",\n+          \"group\": \"3_mcp@2\"\n+        },\n+        {\n+          \"command\": \"intellijStyledSearch.rebuildIndex\",\n+          \"group\": \"4_index@1\"\n+        },\n+        {\n+          \"command\": \"intellijStyledSearch.switchEngine\",\n+          \"group\": \"4_index@2\"\n+        },\n+        {\n+          \"command\": \"intellijStyledSearch.showZoektInfo\",\n+          \"group\": \"4_index@3\"\n+        },\n+        {\n+          \"command\": \"intellijStyledSearch.explainZoektQuery\",\n+          \"group\": \"4_index@4\"\n+        },\n+        {\n+          \"command\": \"intellijStyledSearch.diagnoseFileInIndex\",\n+          \"group\": \"4_index@5\"\n+        },\n+        {\n+          \"command\": \"intellijStyledSearch.reinject\",\n+          \"group\": \"5_recovery@1\"\n+        }\n       ]\n     },\n     \"configuration\": {\n       \"title\": \"IntelliJ Styled Search\",\n@@ -134,8 +248,71 @@\n         \"intellijStyledSearch.searchHistoryLimit\": {\n           \"type\": \"number\",\n           \"default\": 100,\n           \"description\": \"Maximum number of executed search queries to keep in the search history dropdown. Set to 0 to disable storing search history.\"\n+        },\n+        \"intellijStyledSearch.mcpPort\": {\n+          \"type\": \"number\",\n+          \"default\": 8765,\n+          \"description\": \"Localhost port used by the call graph MCP JSON-RPC endpoint when `Start Call Graph MCP Server` is run. Set to 0 to let the OS choose a free port.\"\n+        },\n+        \"intellijStyledSearch.callGraphConcurrency\": {\n+          \"type\": \"number\",\n+          \"default\": 0,\n+          \"minimum\": 0,\n+          \"maximum\": 32,\n+          \"description\": \"Maximum number of source files parsed concurrently when rebuilding the call graph. Set to 0 to auto-size from system parallelism, capped at 32.\"\n+        },\n+        \"intellijStyledSearch.callGraphInlayHints\": {\n+          \"type\": \"boolean\",\n+          \"default\": true,\n+          \"description\": \"Show call graph relation links as inlay hints next to symbols. By default this surfaces callers, usages, and implementations.\"\n+        },\n+        \"intellijStyledSearch.callGraphShowCalleeInlayHints\": {\n+          \"type\": \"boolean\",\n+          \"default\": false,\n+          \"description\": \"Also show callees in call graph inlay hints. Disabled by default because callers and usages are usually more useful for code navigation and agent context.\"\n+        },\n+        \"intellijStyledSearch.callGraphImplementationProvider\": {\n+          \"type\": \"boolean\",\n+          \"default\": true,\n+          \"description\": \"Provide Go to Implementation results from the call graph for interface and abstract symbols.\"\n+        },\n+        \"intellijStyledSearch.callGraphExcludeGlobs\": {\n+          \"type\": \"array\",\n+          \"default\": [\n+            \"**/.venv/**\",\n+            \"**/venv/**\",\n+            \"**/.tox/**\",\n+            \"**/site-packages/**\",\n+            \"**/__pycache__/**\",\n+            \"**/.mypy_cache/**\",\n+            \"**/.pytest_cache/**\"\n+          ],\n+          \"description\": \"Additional glob patterns excluded only from call graph rebuilds.\"\n+        },\n+        \"intellijStyledSearch.callGraphIncludePossibleEdges\": {\n+          \"type\": \"boolean\",\n+          \"default\": false,\n+          \"description\": \"Materialize ambiguous possible call graph edges. Disabled by default to avoid memory explosions in large repositories.\"\n+        },\n+        \"intellijStyledSearch.callGraphIncludeUnresolvedEdges\": {\n+          \"type\": \"boolean\",\n+          \"default\": true,\n+          \"description\": \"Materialize unresolved, dynamic, and external callsites as one dynamic edge per callsite. This keeps dynamic calls visible without exploding ambiguous possible edges.\"\n+        },\n+        \"intellijStyledSearch.callGraphMaxEdges\": {\n+          \"type\": \"number\",\n+          \"default\": 10000000,\n+          \"minimum\": 1000,\n+          \"description\": \"Maximum unique materialized call graph edges stored in memory during a rebuild.\"\n+        },\n+        \"intellijStyledSearch.callGraphMaxPossibleTargetsPerCall\": {\n+          \"type\": \"number\",\n+          \"default\": 8,\n+          \"minimum\": 1,\n+          \"maximum\": 40,\n+          \"description\": \"Maximum possible target edges per ambiguous call when possible edges are enabled.\"\n         }\n       }\n     }\n   },\n"
                },
                {
                    "date": 1777959483124,
                    "content": "Index: \n===================================================================\n--- \n+++ \n@@ -1,9 +1,9 @@\n {\n   \"name\": \"intellij-styled-search\",\n   \"displayName\": \"IntelliJ Styled Search\",\n   \"description\": \"IntelliJ IDEA style project search — peek-like movable panel with workspace file results\",\n-  \"version\": \"0.1.6\",\n+  \"version\": \"0.1.662\",\n   \"publisher\": \"newdlops\",\n   \"license\": \"MIT\",\n   \"icon\": \"resources/icon.png\",\n   \"repository\": {\n@@ -44,12 +44,22 @@\n         \"category\": \"IntelliJ Search\"\n       },\n       {\n         \"command\": \"intellijStyledSearch.reinject\",\n-        \"title\": \"Reinject Renderer Patch (Recovery)\",\n+        \"title\": \"Reinject Renderer Patch (Uses CDP)\",\n         \"category\": \"IntelliJ Search\"\n       },\n       {\n+        \"command\": \"intellijStyledSearch.stopMonacoCapture\",\n+        \"title\": \"Stop Monaco Capture (Safe)\",\n+        \"category\": \"IntelliJ Search\"\n+      },\n+      {\n+        \"command\": \"intellijStyledSearch.recoverRendererUi\",\n+        \"title\": \"Recover VS Code UI Responsiveness (Safe)\",\n+        \"category\": \"IntelliJ Search\"\n+      },\n+      {\n         \"command\": \"intellijStyledSearch.rebuildIndex\",\n         \"title\": \"Rebuild Search Index\",\n         \"category\": \"IntelliJ Search\"\n       },\n@@ -78,8 +88,13 @@\n         \"title\": \"Rebuild Call Graph\",\n         \"category\": \"IntelliJ Search\"\n       },\n       {\n+        \"command\": \"intellijStyledSearch.forceRebuildCallGraph\",\n+        \"title\": \"Force Rebuild Call Graph\",\n+        \"category\": \"IntelliJ Search\"\n+      },\n+      {\n         \"command\": \"intellijStyledSearch.showCallGraphInfo\",\n         \"title\": \"Show Call Graph Info\",\n         \"category\": \"IntelliJ Search\"\n       },\n@@ -172,12 +187,16 @@\n           \"command\": \"intellijStyledSearch.rebuildCallGraph\",\n           \"group\": \"2_callGraph@5\"\n         },\n         {\n-          \"command\": \"intellijStyledSearch.showCallGraphInfo\",\n+          \"command\": \"intellijStyledSearch.forceRebuildCallGraph\",\n           \"group\": \"2_callGraph@6\"\n         },\n         {\n+          \"command\": \"intellijStyledSearch.showCallGraphInfo\",\n+          \"group\": \"2_callGraph@7\"\n+        },\n+        {\n           \"command\": \"intellijStyledSearch.startMcpServer\",\n           \"group\": \"3_mcp@1\"\n         },\n         {\n@@ -206,8 +225,16 @@\n         },\n         {\n           \"command\": \"intellijStyledSearch.reinject\",\n           \"group\": \"5_recovery@1\"\n+        },\n+        {\n+          \"command\": \"intellijStyledSearch.stopMonacoCapture\",\n+          \"group\": \"5_recovery@2\"\n+        },\n+        {\n+          \"command\": \"intellijStyledSearch.recoverRendererUi\",\n+          \"group\": \"5_recovery@3\"\n         }\n       ]\n     },\n     \"configuration\": {\n@@ -223,19 +250,76 @@\n           \"markdownDescription\": \"Search engine to use. `zoekt` runs the Rust local shard/mmap engine with automatic codesearch fallback when the runtime is unavailable or still warming up. `codesearch` uses the existing TypeScript planner plus ripgrep verifier.\"\n         },\n         \"intellijStyledSearch.excludeGlobs\": {\n           \"type\": \"array\",\n-          \"default\": [\n-            \"**/node_modules/**\",\n-            \"**/.git/**\",\n-            \"**/out/**\",\n-            \"**/dist/**\",\n-            \"**/build/**\",\n-            \"**/.next/**\",\n-            \"**/coverage/**\"\n-          ],\n-          \"description\": \"Glob patterns to exclude from search.\"\n+          \"default\": [],\n+          \"description\": \"User-controlled glob patterns to exclude from search. Binary and oversized files are filtered separately.\"\n         },\n+        \"intellijStyledSearch.searchOnOpen\": {\n+          \"type\": \"boolean\",\n+          \"default\": false,\n+          \"description\": \"Run the initial search immediately when Search UI opens with a prefilled query. Disabled by default so opening the UI only renders the lightweight query shell; press Enter or Run to search.\"\n+        },\n+        \"intellijStyledSearch.zoektIncrementalFileUpdates\": {\n+          \"type\": \"boolean\",\n+          \"default\": true,\n+          \"description\": \"Keep the zoekt index updated from confirmed editor saves and VS Code delete/rename operations. Disable to stop background zoekt update processes; manual index rebuild will still refresh search results.\"\n+        },\n+        \"intellijStyledSearch.zoektPrewarmOnActivation\": {\n+          \"type\": \"boolean\",\n+          \"default\": false,\n+          \"description\": \"Build or prepare zoekt on extension activation. Disabled by default so startup does not run cargo build or workspace indexing.\"\n+        },\n+        \"intellijStyledSearch.zoektBuildBinaryInBackgroundOnSearch\": {\n+          \"type\": \"boolean\",\n+          \"default\": false,\n+          \"description\": \"When zoekt is selected but the binary is missing, schedule a delayed background build after a search. Disabled by default; use Rebuild Search Index to start this work explicitly.\"\n+        },\n+        \"intellijStyledSearch.zoektIndexInBackgroundOnSearch\": {\n+          \"type\": \"boolean\",\n+          \"default\": false,\n+          \"description\": \"When zoekt is selected but the index is missing, schedule delayed background indexing after a search. Disabled by default; searches show a rebuild recommendation and use fallback until Rebuild Search Index is run.\"\n+        },\n+        \"intellijStyledSearch.zoektBackgroundBuildDelayMs\": {\n+          \"type\": \"number\",\n+          \"default\": 30000,\n+          \"minimum\": 0,\n+          \"maximum\": 300000,\n+          \"description\": \"Delay before an opt-in background zoekt binary build starts.\"\n+        },\n+        \"intellijStyledSearch.zoektBackgroundIndexDelayMs\": {\n+          \"type\": \"number\",\n+          \"default\": 30000,\n+          \"minimum\": 0,\n+          \"maximum\": 300000,\n+          \"description\": \"Delay before an opt-in background zoekt index build starts.\"\n+        },\n+        \"intellijStyledSearch.zoektWatchExternalFileDeletes\": {\n+          \"type\": \"boolean\",\n+          \"default\": false,\n+          \"description\": \"Watch external filesystem delete events for zoekt incremental updates. Disabled by default so the extension does not subscribe to every workspace file event; saved editor documents and VS Code delete/rename operations are still tracked.\"\n+        },\n+        \"intellijStyledSearch.zoektUpdateDebounceMs\": {\n+          \"type\": \"number\",\n+          \"default\": 5000,\n+          \"minimum\": 250,\n+          \"maximum\": 60000,\n+          \"description\": \"Debounce window for batching workspace file events before running a zoekt incremental update.\"\n+        },\n+        \"intellijStyledSearch.zoektUpdateCooldownMs\": {\n+          \"type\": \"number\",\n+          \"default\": 5000,\n+          \"minimum\": 0,\n+          \"maximum\": 60000,\n+          \"description\": \"Minimum cooldown after a zoekt incremental update before another update may run.\"\n+        },\n+        \"intellijStyledSearch.zoektUpdateLogMinIntervalMs\": {\n+          \"type\": \"number\",\n+          \"default\": 10000,\n+          \"minimum\": 0,\n+          \"maximum\": 300000,\n+          \"description\": \"Minimum interval between routine zoekt update log lines. Suppressed update logs are summarized in the next emitted line.\"\n+        },\n         \"intellijStyledSearch.maxFileSize\": {\n           \"type\": \"number\",\n           \"default\": 1048576,\n           \"description\": \"Maximum file size (bytes) to include in search.\"\n@@ -249,20 +333,142 @@\n           \"type\": \"number\",\n           \"default\": 100,\n           \"description\": \"Maximum number of executed search queries to keep in the search history dropdown. Set to 0 to disable storing search history.\"\n         },\n+        \"intellijStyledSearch.disableMonacoCapture\": {\n+          \"type\": \"boolean\",\n+          \"default\": false,\n+          \"description\": \"Disable Monaco capture/prototype probing for search previews. When disabled, previews use a real Monaco editor with shared buffers, language services, minimap, syntax highlighting, and save support.\"\n+        },\n+        \"intellijStyledSearch.closeMainInspectorAfterSearch\": {\n+          \"type\": \"boolean\",\n+          \"default\": true,\n+          \"description\": \"Close VS Code's shared main-process inspector after Search UI work. Enabled by default to keep the VS Code renderer responsive after CDP-based UI injection.\"\n+        },\n+        \"intellijStyledSearch.rendererPerfDiagnostics\": {\n+          \"type\": \"boolean\",\n+          \"default\": true,\n+          \"description\": \"Enable renderer performance tracing for Search UI diagnosis. When enabled, panel open records frame gaps, event delay, event timing, long tasks, long animation frames, DOM counts, memory and phase markers in batched renderer logs.\"\n+        },\n+        \"intellijStyledSearch.rendererSafetyDiagnostics\": {\n+          \"type\": \"boolean\",\n+          \"default\": false,\n+          \"description\": \"Enable Search UI renderer safety snapshots in the output log. Disabled by default because each snapshot evaluates JavaScript in the VS Code renderer.\"\n+        },\n+        \"intellijStyledSearch.rendererInlayClickHook\": {\n+          \"type\": \"boolean\",\n+          \"default\": true,\n+          \"description\": \"Enable the renderer-level direct click hook for call graph inlay hints. Enabled by default because VS Code native inlay commands may require hover/link activation instead of a single click.\"\n+        },\n+        \"intellijStyledSearch.disposeRendererPatchOnHide\": {\n+          \"type\": \"boolean\",\n+          \"default\": false,\n+          \"description\": \"Fully dispose the injected Search UI renderer patch when the panel is hidden. Disabled by default so direct inlay clicks can reuse the lightweight renderer hook without repeated CDP reinjection.\"\n+        },\n+        \"intellijStyledSearch.keepCdpOpenWhileSearchUiVisible\": {\n+          \"type\": \"boolean\",\n+          \"default\": true,\n+          \"description\": \"Keep the CDP bridge open while the Search UI panel is visible. Enabled by default to avoid repeated SIGUSR1/inspector reconnects during typing and incremental searches; cleanup still runs when the panel is hidden.\"\n+        },\n+        \"intellijStyledSearch.rendererBridgeSingletonIdleMs\": {\n+          \"type\": \"number\",\n+          \"default\": 30000,\n+          \"minimum\": 1000,\n+          \"maximum\": 300000,\n+          \"description\": \"How long to keep the renderer patch bridge warm after the Search UI is hidden when direct inlay clicks are enabled. This avoids repeatedly reacquiring the renderer patch during inlay navigation.\"\n+        },\n+        \"intellijStyledSearch.suspendIntelliSenseRecursionCaptureDuringSearchUi\": {\n+          \"type\": \"boolean\",\n+          \"default\": true,\n+          \"description\": \"Temporarily stop and suppress IntelliSense Recursion renderer capture while the Search UI is visible. This avoids overlapping renderer prototype hooks from slowing VS Code.\"\n+        },\n         \"intellijStyledSearch.mcpPort\": {\n           \"type\": \"number\",\n           \"default\": 8765,\n           \"description\": \"Localhost port used by the call graph MCP JSON-RPC endpoint when `Start Call Graph MCP Server` is run. Set to 0 to let the OS choose a free port.\"\n         },\n+        \"intellijStyledSearch.callGraphWatchExternalFileChanges\": {\n+          \"type\": \"boolean\",\n+          \"default\": false,\n+          \"description\": \"Watch external filesystem create/change/delete events for call graph incremental updates. Disabled by default so call graph updates only follow confirmed VS Code save/create/delete/rename operations.\"\n+        },\n         \"intellijStyledSearch.callGraphConcurrency\": {\n           \"type\": \"number\",\n           \"default\": 0,\n           \"minimum\": 0,\n           \"maximum\": 32,\n-          \"description\": \"Maximum number of source files parsed concurrently when rebuilding the call graph. Set to 0 to auto-size from system parallelism, capped at 32.\"\n+          \"description\": \"Maximum number of source files parsed concurrently when rebuilding the call graph. Set to 0 to auto-size from system parallelism. The effective worker count is also capped by intellijStyledSearch.callGraphMemoryBudgetMb.\"\n         },\n+        \"intellijStyledSearch.callGraphCpuBudgetPercent\": {\n+          \"type\": \"number\",\n+          \"default\": 35,\n+          \"minimum\": 5,\n+          \"maximum\": 100,\n+          \"description\": \"Approximate extension-host CPU duty cycle used by call graph parsing. Lower values insert more idle time between parsed files so VS Code remains responsive during rebuild.\"\n+        },\n+        \"intellijStyledSearch.callGraphMaxParserPauseMs\": {\n+          \"type\": \"number\",\n+          \"default\": 2000,\n+          \"minimum\": 0,\n+          \"maximum\": 10000,\n+          \"description\": \"Maximum single cooldown pause inserted after a call graph parser slice. Set to 0 to disable the cap.\"\n+        },\n+        \"intellijStyledSearch.callGraphMaxFileSize\": {\n+          \"type\": \"number\",\n+          \"default\": 0,\n+          \"minimum\": 0,\n+          \"maximum\": 9007199254740991,\n+          \"description\": \"Maximum file size in bytes to parse for the call graph. Set to 0 for unlimited parsing.\"\n+        },\n+        \"intellijStyledSearch.callGraphMaxLineLength\": {\n+          \"type\": \"number\",\n+          \"default\": 0,\n+          \"minimum\": 0,\n+          \"maximum\": 1000000,\n+          \"description\": \"Skip call graph parsing for files that contain a line longer than this many characters. Set to 0 for unlimited parsing.\"\n+        },\n+        \"intellijStyledSearch.callGraphMaxLinesPerFile\": {\n+          \"type\": \"number\",\n+          \"default\": 0,\n+          \"minimum\": 0,\n+          \"maximum\": 1000000,\n+          \"description\": \"Skip call graph parsing for files with more lines than this limit. Set to 0 for unlimited parsing.\"\n+        },\n+        \"intellijStyledSearch.callGraphMaxReferenceCandidatesPerFile\": {\n+          \"type\": \"number\",\n+          \"default\": 0,\n+          \"minimum\": 0,\n+          \"maximum\": 1000000,\n+          \"description\": \"Maximum usage/reference candidates extracted from a single file. Set to 0 for unlimited extraction.\"\n+        },\n+        \"intellijStyledSearch.callGraphMaxCallsites\": {\n+          \"type\": \"number\",\n+          \"default\": 0,\n+          \"minimum\": 0,\n+          \"maximum\": 9007199254740991,\n+          \"description\": \"Maximum callsites kept across one call graph rebuild. Set to 0 for unlimited extraction. Positive values intentionally cap the index and may drop callsites.\"\n+        },\n+        \"intellijStyledSearch.callGraphMaxReferenceCandidates\": {\n+          \"type\": \"number\",\n+          \"default\": 0,\n+          \"minimum\": 0,\n+          \"maximum\": 9007199254740991,\n+          \"description\": \"Maximum usage/reference candidates kept across one call graph rebuild. Set to 0 for unlimited extraction. Positive values intentionally cap the index and may drop references.\"\n+        },\n+        \"intellijStyledSearch.callGraphMemoryBudgetMb\": {\n+          \"type\": \"number\",\n+          \"default\": 1024,\n+          \"minimum\": 256,\n+          \"maximum\": 16384,\n+          \"description\": \"Approximate call graph rebuild memory budget in MB. This caps parser concurrency so large repositories do not start too many parser workers for the extension host heap.\"\n+        },\n+        \"intellijStyledSearch.callGraphMaxAssignedFunctionNamesPerFile\": {\n+          \"type\": \"number\",\n+          \"default\": 0,\n+          \"minimum\": 0,\n+          \"maximum\": 100000,\n+          \"description\": \"Maximum anonymous-assignment function names scanned per file for usage detection. Set to 0 for unlimited extraction.\"\n+        },\n         \"intellijStyledSearch.callGraphInlayHints\": {\n           \"type\": \"boolean\",\n           \"default\": true,\n           \"description\": \"Show call graph relation links as inlay hints next to symbols. By default this surfaces callers, usages, and implementations.\"\n@@ -278,34 +484,27 @@\n           \"description\": \"Provide Go to Implementation results from the call graph for interface and abstract symbols.\"\n         },\n         \"intellijStyledSearch.callGraphExcludeGlobs\": {\n           \"type\": \"array\",\n-          \"default\": [\n-            \"**/.venv/**\",\n-            \"**/venv/**\",\n-            \"**/.tox/**\",\n-            \"**/site-packages/**\",\n-            \"**/__pycache__/**\",\n-            \"**/.mypy_cache/**\",\n-            \"**/.pytest_cache/**\"\n-          ],\n-          \"description\": \"Additional glob patterns excluded only from call graph rebuilds.\"\n+          \"default\": [],\n+          \"description\": \"User-controlled glob patterns excluded only from call graph rebuilds. Binary and oversized files are filtered separately.\"\n         },\n         \"intellijStyledSearch.callGraphIncludePossibleEdges\": {\n           \"type\": \"boolean\",\n           \"default\": false,\n           \"description\": \"Materialize ambiguous possible call graph edges. Disabled by default to avoid memory explosions in large repositories.\"\n         },\n         \"intellijStyledSearch.callGraphIncludeUnresolvedEdges\": {\n           \"type\": \"boolean\",\n-          \"default\": true,\n-          \"description\": \"Materialize unresolved, dynamic, and external callsites as one dynamic edge per callsite. This keeps dynamic calls visible without exploding ambiguous possible edges.\"\n+          \"default\": false,\n+          \"description\": \"Materialize unresolved, dynamic, and external callsites as one dynamic edge per callsite. Disabled by default to keep large-repository graph indexes bounded.\"\n         },\n         \"intellijStyledSearch.callGraphMaxEdges\": {\n           \"type\": \"number\",\n-          \"default\": 10000000,\n-          \"minimum\": 1000,\n-          \"description\": \"Maximum unique materialized call graph edges stored in memory during a rebuild.\"\n+          \"default\": 0,\n+          \"minimum\": 0,\n+          \"maximum\": 9007199254740991,\n+          \"description\": \"Maximum unique materialized call graph edges stored in memory during a rebuild. Set to 0 for unlimited materialization.\"\n         },\n         \"intellijStyledSearch.callGraphMaxPossibleTargetsPerCall\": {\n           \"type\": \"number\",\n           \"default\": 8,\n"
                },
                {
                    "date": 1777962337182,
                    "content": "Index: \n===================================================================\n--- \n+++ \n@@ -1,9 +1,9 @@\n {\n   \"name\": \"intellij-styled-search\",\n   \"displayName\": \"IntelliJ Styled Search\",\n   \"description\": \"IntelliJ IDEA style project search — peek-like movable panel with workspace file results\",\n-  \"version\": \"0.1.662\",\n+  \"version\": \"0.1.663\",\n   \"publisher\": \"newdlops\",\n   \"license\": \"MIT\",\n   \"icon\": \"resources/icon.png\",\n   \"repository\": {\n@@ -455,12 +455,12 @@\n           \"description\": \"Maximum usage/reference candidates kept across one call graph rebuild. Set to 0 for unlimited extraction. Positive values intentionally cap the index and may drop references.\"\n         },\n         \"intellijStyledSearch.callGraphMemoryBudgetMb\": {\n           \"type\": \"number\",\n-          \"default\": 1024,\n+          \"default\": 8192,\n           \"minimum\": 256,\n           \"maximum\": 16384,\n-          \"description\": \"Approximate call graph rebuild memory budget in MB. This caps parser concurrency so large repositories do not start too many parser workers for the extension host heap.\"\n+          \"description\": \"Approximate call graph rebuild memory budget in MB. Full rebuilds run in a separate worker process launched with this V8 max-old-space-size, and the same value controls parser concurrency and heap pressure thresholds.\"\n         },\n         \"intellijStyledSearch.callGraphMaxAssignedFunctionNamesPerFile\": {\n           \"type\": \"number\",\n           \"default\": 0,\n@@ -516,10 +516,11 @@\n     }\n   },\n   \"scripts\": {\n     \"bundle:monaco\": \"node scripts/bundleMonaco.js\",\n+    \"bundle:callgraph-worker\": \"node scripts/bundleCallGraphWorker.js\",\n     \"bench:zoekt\": \"node scripts/runZoektBenchmark.js\",\n-    \"compile\": \"npm run bundle:monaco && tsc -p ./\",\n+    \"compile\": \"npm run bundle:monaco && tsc -p ./ && npm run bundle:callgraph-worker\",\n     \"watch\": \"tsc -watch -p ./\",\n     \"vscode:prepublish\": \"npm run compile\",\n     \"pretest\": \"npm run compile\",\n     \"test\": \"vscode-test\"\n"
                },
                {
                    "date": 1777963401340,
                    "content": "Index: \n===================================================================\n--- \n+++ \n@@ -1,9 +1,9 @@\n {\n   \"name\": \"intellij-styled-search\",\n   \"displayName\": \"IntelliJ Styled Search\",\n   \"description\": \"IntelliJ IDEA style project search — peek-like movable panel with workspace file results\",\n-  \"version\": \"0.1.663\",\n+  \"version\": \"0.1.664\",\n   \"publisher\": \"newdlops\",\n   \"license\": \"MIT\",\n   \"icon\": \"resources/icon.png\",\n   \"repository\": {\n@@ -402,9 +402,9 @@\n           \"type\": \"number\",\n           \"default\": 35,\n           \"minimum\": 5,\n           \"maximum\": 100,\n-          \"description\": \"Approximate extension-host CPU duty cycle used by call graph parsing. Lower values insert more idle time between parsed files so VS Code remains responsive during rebuild.\"\n+          \"description\": \"Approximate call graph worker CPU duty cycle used by parsing. Lower values insert more idle time between parsed files so VS Code remains responsive during rebuild.\"\n         },\n         \"intellijStyledSearch.callGraphMaxParserPauseMs\": {\n           \"type\": \"number\",\n           \"default\": 2000,\n@@ -457,10 +457,10 @@\n         \"intellijStyledSearch.callGraphMemoryBudgetMb\": {\n           \"type\": \"number\",\n           \"default\": 8192,\n           \"minimum\": 256,\n-          \"maximum\": 16384,\n-          \"description\": \"Approximate call graph rebuild memory budget in MB. Full rebuilds run in a separate worker process launched with this V8 max-old-space-size, and the same value controls parser concurrency and heap pressure thresholds.\"\n+          \"maximum\": 32768,\n+          \"description\": \"Approximate call graph rebuild memory budget in MB. Full rebuilds run in a separate worker process launched with this V8 max-old-space-size; the default is 8192MB and the worker can be raised up to 32768MB.\"\n         },\n         \"intellijStyledSearch.callGraphMaxAssignedFunctionNamesPerFile\": {\n           \"type\": \"number\",\n           \"default\": 0,\n"
                },
                {
                    "date": 1777963710467,
                    "content": "Index: \n===================================================================\n--- \n+++ \n@@ -1,9 +1,9 @@\n {\n   \"name\": \"intellij-styled-search\",\n   \"displayName\": \"IntelliJ Styled Search\",\n   \"description\": \"IntelliJ IDEA style project search — peek-like movable panel with workspace file results\",\n-  \"version\": \"0.1.664\",\n+  \"version\": \"0.1.665\",\n   \"publisher\": \"newdlops\",\n   \"license\": \"MIT\",\n   \"icon\": \"resources/icon.png\",\n   \"repository\": {\n"
                },
                {
                    "date": 1777966143857,
                    "content": "Index: \n===================================================================\n--- \n+++ \n@@ -1,9 +1,9 @@\n {\n   \"name\": \"intellij-styled-search\",\n   \"displayName\": \"IntelliJ Styled Search\",\n   \"description\": \"IntelliJ IDEA style project search — peek-like movable panel with workspace file results\",\n-  \"version\": \"0.1.665\",\n+  \"version\": \"0.1.666\",\n   \"publisher\": \"newdlops\",\n   \"license\": \"MIT\",\n   \"icon\": \"resources/icon.png\",\n   \"repository\": {\n@@ -460,8 +460,13 @@\n           \"minimum\": 256,\n           \"maximum\": 32768,\n           \"description\": \"Approximate call graph rebuild memory budget in MB. Full rebuilds run in a separate worker process launched with this V8 max-old-space-size; the default is 8192MB and the worker can be raised up to 32768MB.\"\n         },\n+        \"intellijStyledSearch.callGraphNodePath\": {\n+          \"type\": \"string\",\n+          \"default\": \"\",\n+          \"description\": \"Optional absolute path to a real Node.js executable used for call graph rebuild workers. Leave empty to auto-detect Node from PATH and common version-manager locations.\"\n+        },\n         \"intellijStyledSearch.callGraphMaxAssignedFunctionNamesPerFile\": {\n           \"type\": \"number\",\n           \"default\": 0,\n           \"minimum\": 0,\n"
                },
                {
                    "date": 1777966762826,
                    "content": "Index: \n===================================================================\n--- \n+++ \n@@ -1,9 +1,9 @@\n {\n   \"name\": \"intellij-styled-search\",\n   \"displayName\": \"IntelliJ Styled Search\",\n   \"description\": \"IntelliJ IDEA style project search — peek-like movable panel with workspace file results\",\n-  \"version\": \"0.1.666\",\n+  \"version\": \"0.1.667\",\n   \"publisher\": \"newdlops\",\n   \"license\": \"MIT\",\n   \"icon\": \"resources/icon.png\",\n   \"repository\": {\n"
                },
                {
                    "date": 1777967885846,
                    "content": "Index: \n===================================================================\n--- \n+++ \n@@ -1,9 +1,9 @@\n {\n   \"name\": \"intellij-styled-search\",\n   \"displayName\": \"IntelliJ Styled Search\",\n   \"description\": \"IntelliJ IDEA style project search — peek-like movable panel with workspace file results\",\n-  \"version\": \"0.1.667\",\n+  \"version\": \"0.1.668\",\n   \"publisher\": \"newdlops\",\n   \"license\": \"MIT\",\n   \"icon\": \"resources/icon.png\",\n   \"repository\": {\n@@ -392,12 +392,12 @@\n           \"description\": \"Watch external filesystem create/change/delete events for call graph incremental updates. Disabled by default so call graph updates only follow confirmed VS Code save/create/delete/rename operations.\"\n         },\n         \"intellijStyledSearch.callGraphConcurrency\": {\n           \"type\": \"number\",\n-          \"default\": 0,\n+          \"default\": 32,\n           \"minimum\": 0,\n           \"maximum\": 32,\n-          \"description\": \"Maximum number of source files parsed concurrently when rebuilding the call graph. Set to 0 to auto-size from system parallelism. The effective worker count is also capped by intellijStyledSearch.callGraphMemoryBudgetMb.\"\n+          \"description\": \"Maximum number of source files parsed concurrently when rebuilding the call graph. Defaults to 32 for the Rust native graph indexer. Set to 0 to auto-size from system parallelism. The effective worker count is also capped by intellijStyledSearch.callGraphMemoryBudgetMb.\"\n         },\n         \"intellijStyledSearch.callGraphCpuBudgetPercent\": {\n           \"type\": \"number\",\n           \"default\": 35,\n"
                },
                {
                    "date": 1777969384278,
                    "content": "Index: \n===================================================================\n--- \n+++ \n@@ -1,9 +1,9 @@\n {\n   \"name\": \"intellij-styled-search\",\n   \"displayName\": \"IntelliJ Styled Search\",\n   \"description\": \"IntelliJ IDEA style project search — peek-like movable panel with workspace file results\",\n-  \"version\": \"0.1.668\",\n+  \"version\": \"0.1.669\",\n   \"publisher\": \"newdlops\",\n   \"license\": \"MIT\",\n   \"icon\": \"resources/icon.png\",\n   \"repository\": {\n"
                },
                {
                    "date": 1777970874023,
                    "content": "Index: \n===================================================================\n--- \n+++ \n@@ -1,9 +1,9 @@\n {\n   \"name\": \"intellij-styled-search\",\n   \"displayName\": \"IntelliJ Styled Search\",\n   \"description\": \"IntelliJ IDEA style project search — peek-like movable panel with workspace file results\",\n-  \"version\": \"0.1.669\",\n+  \"version\": \"0.1.670\",\n   \"publisher\": \"newdlops\",\n   \"license\": \"MIT\",\n   \"icon\": \"resources/icon.png\",\n   \"repository\": {\n"
                },
                {
                    "date": 1777972734235,
                    "content": "Index: \n===================================================================\n--- \n+++ \n@@ -1,9 +1,9 @@\n {\n   \"name\": \"intellij-styled-search\",\n   \"displayName\": \"IntelliJ Styled Search\",\n   \"description\": \"IntelliJ IDEA style project search — peek-like movable panel with workspace file results\",\n-  \"version\": \"0.1.670\",\n+  \"version\": \"0.1.671\",\n   \"publisher\": \"newdlops\",\n   \"license\": \"MIT\",\n   \"icon\": \"resources/icon.png\",\n   \"repository\": {\n"
                },
                {
                    "date": 1777973920216,
                    "content": "Index: \n===================================================================\n--- \n+++ \n@@ -1,9 +1,9 @@\n {\n   \"name\": \"intellij-styled-search\",\n   \"displayName\": \"IntelliJ Styled Search\",\n   \"description\": \"IntelliJ IDEA style project search — peek-like movable panel with workspace file results\",\n-  \"version\": \"0.1.671\",\n+  \"version\": \"0.1.672\",\n   \"publisher\": \"newdlops\",\n   \"license\": \"MIT\",\n   \"icon\": \"resources/icon.png\",\n   \"repository\": {\n"
                },
                {
                    "date": 1777975732077,
                    "content": "Index: \n===================================================================\n--- \n+++ \n@@ -1,9 +1,9 @@\n {\n   \"name\": \"intellij-styled-search\",\n   \"displayName\": \"IntelliJ Styled Search\",\n   \"description\": \"IntelliJ IDEA style project search — peek-like movable panel with workspace file results\",\n-  \"version\": \"0.1.672\",\n+  \"version\": \"0.1.673\",\n   \"publisher\": \"newdlops\",\n   \"license\": \"MIT\",\n   \"icon\": \"resources/icon.png\",\n   \"repository\": {\n"
                },
                {
                    "date": 1777978772470,
                    "content": "Index: \n===================================================================\n--- \n+++ \n@@ -1,9 +1,9 @@\n {\n   \"name\": \"intellij-styled-search\",\n   \"displayName\": \"IntelliJ Styled Search\",\n   \"description\": \"IntelliJ IDEA style project search — peek-like movable panel with workspace file results\",\n-  \"version\": \"0.1.673\",\n+  \"version\": \"0.1.674\",\n   \"publisher\": \"newdlops\",\n   \"license\": \"MIT\",\n   \"icon\": \"resources/icon.png\",\n   \"repository\": {\n"
                },
                {
                    "date": 1777984346697,
                    "content": "Index: \n===================================================================\n--- \n+++ \n@@ -1,9 +1,9 @@\n {\n   \"name\": \"intellij-styled-search\",\n   \"displayName\": \"IntelliJ Styled Search\",\n   \"description\": \"IntelliJ IDEA style project search — peek-like movable panel with workspace file results\",\n-  \"version\": \"0.1.674\",\n+  \"version\": \"0.1.675\",\n   \"publisher\": \"newdlops\",\n   \"license\": \"MIT\",\n   \"icon\": \"resources/icon.png\",\n   \"repository\": {\n"
                },
                {
                    "date": 1777987117872,
                    "content": "Index: \n===================================================================\n--- \n+++ \n@@ -1,9 +1,9 @@\n {\n   \"name\": \"intellij-styled-search\",\n   \"displayName\": \"IntelliJ Styled Search\",\n   \"description\": \"IntelliJ IDEA style project search — peek-like movable panel with workspace file results\",\n-  \"version\": \"0.1.675\",\n+  \"version\": \"0.1.676\",\n   \"publisher\": \"newdlops\",\n   \"license\": \"MIT\",\n   \"icon\": \"resources/icon.png\",\n   \"repository\": {\n"
                },
                {
                    "date": 1777987823185,
                    "content": "Index: \n===================================================================\n--- \n+++ \n@@ -1,9 +1,9 @@\n {\n   \"name\": \"intellij-styled-search\",\n   \"displayName\": \"IntelliJ Styled Search\",\n   \"description\": \"IntelliJ IDEA style project search — peek-like movable panel with workspace file results\",\n-  \"version\": \"0.1.676\",\n+  \"version\": \"0.1.677\",\n   \"publisher\": \"newdlops\",\n   \"license\": \"MIT\",\n   \"icon\": \"resources/icon.png\",\n   \"repository\": {\n@@ -392,12 +392,12 @@\n           \"description\": \"Watch external filesystem create/change/delete events for call graph incremental updates. Disabled by default so call graph updates only follow confirmed VS Code save/create/delete/rename operations.\"\n         },\n         \"intellijStyledSearch.callGraphConcurrency\": {\n           \"type\": \"number\",\n-          \"default\": 32,\n+          \"default\": 64,\n           \"minimum\": 0,\n-          \"maximum\": 32,\n-          \"description\": \"Maximum number of source files parsed concurrently when rebuilding the call graph. Defaults to 32 for the Rust native graph indexer. Set to 0 to auto-size from system parallelism. The effective worker count is also capped by intellijStyledSearch.callGraphMemoryBudgetMb.\"\n+          \"maximum\": 64,\n+          \"description\": \"Maximum number of source files parsed concurrently when rebuilding the call graph. Defaults to 64 for the Rust native graph indexer. Set to 0 to auto-size from system parallelism. The effective worker count is also capped by intellijStyledSearch.callGraphMemoryBudgetMb.\"\n         },\n         \"intellijStyledSearch.callGraphCpuBudgetPercent\": {\n           \"type\": \"number\",\n           \"default\": 35,\n"
                },
                {
                    "date": 1777989376328,
                    "content": "Index: \n===================================================================\n--- \n+++ \n@@ -1,9 +1,9 @@\n {\n   \"name\": \"intellij-styled-search\",\n   \"displayName\": \"IntelliJ Styled Search\",\n   \"description\": \"IntelliJ IDEA style project search — peek-like movable panel with workspace file results\",\n-  \"version\": \"0.1.677\",\n+  \"version\": \"0.1.678\",\n   \"publisher\": \"newdlops\",\n   \"license\": \"MIT\",\n   \"icon\": \"resources/icon.png\",\n   \"repository\": {\n"
                },
                {
                    "date": 1777991505886,
                    "content": "Index: \n===================================================================\n--- \n+++ \n@@ -1,9 +1,9 @@\n {\n   \"name\": \"intellij-styled-search\",\n   \"displayName\": \"IntelliJ Styled Search\",\n   \"description\": \"IntelliJ IDEA style project search — peek-like movable panel with workspace file results\",\n-  \"version\": \"0.1.678\",\n+  \"version\": \"0.1.679\",\n   \"publisher\": \"newdlops\",\n   \"license\": \"MIT\",\n   \"icon\": \"resources/icon.png\",\n   \"repository\": {\n"
                },
                {
                    "date": 1778031230830,
                    "content": "Index: \n===================================================================\n--- \n+++ \n@@ -1,9 +1,9 @@\n {\n   \"name\": \"intellij-styled-search\",\n   \"displayName\": \"IntelliJ Styled Search\",\n   \"description\": \"IntelliJ IDEA style project search — peek-like movable panel with workspace file results\",\n-  \"version\": \"0.1.679\",\n+  \"version\": \"0.1.680\",\n   \"publisher\": \"newdlops\",\n   \"license\": \"MIT\",\n   \"icon\": \"resources/icon.png\",\n   \"repository\": {\n@@ -16,8 +16,11 @@\n   \"homepage\": \"https://github.com/newdlops/intellij-styled-search#readme\",\n   \"engines\": {\n     \"vscode\": \"^1.75.0\"\n   },\n+  \"bin\": {\n+    \"codeidx-mcp\": \"./out/codeidxMcpCli.js\"\n+  },\n   \"categories\": [\n     \"Other\"\n   ],\n   \"keywords\": [\n@@ -119,14 +122,14 @@\n         \"category\": \"IntelliJ Search\"\n       },\n       {\n         \"command\": \"intellijStyledSearch.startMcpServer\",\n-        \"title\": \"Start Call Graph MCP Server\",\n+        \"title\": \"Start Codeidx MCP Server\",\n         \"category\": \"IntelliJ Search\"\n       },\n       {\n         \"command\": \"intellijStyledSearch.stopMcpServer\",\n-        \"title\": \"Stop Call Graph MCP Server\",\n+        \"title\": \"Stop Codeidx MCP Server\",\n         \"category\": \"IntelliJ Search\"\n       }\n     ],\n     \"keybindings\": [\n@@ -383,10 +386,15 @@\n         },\n         \"intellijStyledSearch.mcpPort\": {\n           \"type\": \"number\",\n           \"default\": 8765,\n-          \"description\": \"Localhost port used by the call graph MCP JSON-RPC endpoint when `Start Call Graph MCP Server` is run. Set to 0 to let the OS choose a free port.\"\n+          \"description\": \"Localhost port used by the codeidx MCP JSON-RPC endpoint when `Start Codeidx MCP Server` is run. Set to 0 to let the OS choose a free port.\"\n         },\n+        \"intellijStyledSearch.mcpAutoStart\": {\n+          \"type\": \"boolean\",\n+          \"default\": false,\n+          \"description\": \"Automatically start the localhost codeidx MCP endpoint when the extension activates. Disabled by default; enable it in trusted workspaces where Codex or Claude should discover the project MCP server without using the Start Codeidx MCP Server command.\"\n+        },\n         \"intellijStyledSearch.callGraphWatchExternalFileChanges\": {\n           \"type\": \"boolean\",\n           \"default\": false,\n           \"description\": \"Watch external filesystem create/change/delete events for call graph incremental updates. Disabled by default so call graph updates only follow confirmed VS Code save/create/delete/rename operations.\"\n"
                },
                {
                    "date": 1778032160760,
                    "content": "Index: \n===================================================================\n--- \n+++ \n@@ -1,9 +1,9 @@\n {\n   \"name\": \"intellij-styled-search\",\n   \"displayName\": \"IntelliJ Styled Search\",\n   \"description\": \"IntelliJ IDEA style project search — peek-like movable panel with workspace file results\",\n-  \"version\": \"0.1.680\",\n+  \"version\": \"0.1.681\",\n   \"publisher\": \"newdlops\",\n   \"license\": \"MIT\",\n   \"icon\": \"resources/icon.png\",\n   \"repository\": {\n@@ -385,15 +385,15 @@\n           \"description\": \"Temporarily stop and suppress IntelliSense Recursion renderer capture while the Search UI is visible. This avoids overlapping renderer prototype hooks from slowing VS Code.\"\n         },\n         \"intellijStyledSearch.mcpPort\": {\n           \"type\": \"number\",\n-          \"default\": 8765,\n-          \"description\": \"Localhost port used by the codeidx MCP JSON-RPC endpoint when `Start Codeidx MCP Server` is run. Set to 0 to let the OS choose a free port.\"\n+          \"default\": 0,\n+          \"description\": \"Localhost port used by the codeidx MCP JSON-RPC endpoint. The default 0 lets the OS choose a free per-window port and records it in the workspace discovery file.\"\n         },\n         \"intellijStyledSearch.mcpAutoStart\": {\n           \"type\": \"boolean\",\n-          \"default\": false,\n-          \"description\": \"Automatically start the localhost codeidx MCP endpoint when the extension activates. Disabled by default; enable it in trusted workspaces where Codex or Claude should discover the project MCP server without using the Start Codeidx MCP Server command.\"\n+          \"default\": true,\n+          \"description\": \"Automatically start the localhost codeidx MCP endpoint in trusted workspaces when the extension activates, so Codex and Claude can discover the project server without using the Start Codeidx MCP Server command.\"\n         },\n         \"intellijStyledSearch.callGraphWatchExternalFileChanges\": {\n           \"type\": \"boolean\",\n           \"default\": false,\n"
                },
                {
                    "date": 1778039073032,
                    "content": "Index: \n===================================================================\n--- \n+++ \n@@ -1,9 +1,9 @@\n {\n   \"name\": \"intellij-styled-search\",\n   \"displayName\": \"IntelliJ Styled Search\",\n   \"description\": \"IntelliJ IDEA style project search — peek-like movable panel with workspace file results\",\n-  \"version\": \"0.1.681\",\n+  \"version\": \"0.1.682\",\n   \"publisher\": \"newdlops\",\n   \"license\": \"MIT\",\n   \"icon\": \"resources/icon.png\",\n   \"repository\": {\n"
                },
                {
                    "date": 1778042519681,
                    "content": "Index: \n===================================================================\n--- \n+++ \n@@ -1,9 +1,9 @@\n {\n   \"name\": \"intellij-styled-search\",\n   \"displayName\": \"IntelliJ Styled Search\",\n   \"description\": \"IntelliJ IDEA style project search — peek-like movable panel with workspace file results\",\n-  \"version\": \"0.1.682\",\n+  \"version\": \"0.1.683\",\n   \"publisher\": \"newdlops\",\n   \"license\": \"MIT\",\n   \"icon\": \"resources/icon.png\",\n   \"repository\": {\n"
                },
                {
                    "date": 1778044035343,
                    "content": "Index: \n===================================================================\n--- \n+++ \n@@ -1,9 +1,9 @@\n {\n   \"name\": \"intellij-styled-search\",\n   \"displayName\": \"IntelliJ Styled Search\",\n   \"description\": \"IntelliJ IDEA style project search — peek-like movable panel with workspace file results\",\n-  \"version\": \"0.1.683\",\n+  \"version\": \"0.1.684\",\n   \"publisher\": \"newdlops\",\n   \"license\": \"MIT\",\n   \"icon\": \"resources/icon.png\",\n   \"repository\": {\n"
                },
                {
                    "date": 1778046534705,
                    "content": "Index: \n===================================================================\n--- \n+++ \n@@ -1,9 +1,9 @@\n {\n   \"name\": \"intellij-styled-search\",\n   \"displayName\": \"IntelliJ Styled Search\",\n   \"description\": \"IntelliJ IDEA style project search — peek-like movable panel with workspace file results\",\n-  \"version\": \"0.1.684\",\n+  \"version\": \"0.1.685\",\n   \"publisher\": \"newdlops\",\n   \"license\": \"MIT\",\n   \"icon\": \"resources/icon.png\",\n   \"repository\": {\n"
                },
                {
                    "date": 1778050147808,
                    "content": "Index: \n===================================================================\n--- \n+++ \n@@ -1,9 +1,9 @@\n {\n   \"name\": \"intellij-styled-search\",\n   \"displayName\": \"IntelliJ Styled Search\",\n   \"description\": \"IntelliJ IDEA style project search — peek-like movable panel with workspace file results\",\n-  \"version\": \"0.1.685\",\n+  \"version\": \"0.1.686\",\n   \"publisher\": \"newdlops\",\n   \"license\": \"MIT\",\n   \"icon\": \"resources/icon.png\",\n   \"repository\": {\n"
                },
                {
                    "date": 1778051956536,
                    "content": "Index: \n===================================================================\n--- \n+++ \n@@ -1,9 +1,9 @@\n {\n   \"name\": \"intellij-styled-search\",\n   \"displayName\": \"IntelliJ Styled Search\",\n   \"description\": \"IntelliJ IDEA style project search — peek-like movable panel with workspace file results\",\n-  \"version\": \"0.1.686\",\n+  \"version\": \"0.1.687\",\n   \"publisher\": \"newdlops\",\n   \"license\": \"MIT\",\n   \"icon\": \"resources/icon.png\",\n   \"repository\": {\n"
                },
                {
                    "date": 1778059199686,
                    "content": "Index: \n===================================================================\n--- \n+++ \n@@ -1,9 +1,9 @@\n {\n   \"name\": \"intellij-styled-search\",\n   \"displayName\": \"IntelliJ Styled Search\",\n   \"description\": \"IntelliJ IDEA style project search — peek-like movable panel with workspace file results\",\n-  \"version\": \"0.1.687\",\n+  \"version\": \"0.1.688\",\n   \"publisher\": \"newdlops\",\n   \"license\": \"MIT\",\n   \"icon\": \"resources/icon.png\",\n   \"repository\": {\n"
                },
                {
                    "date": 1778062266453,
                    "content": "Index: \n===================================================================\n--- \n+++ \n@@ -1,9 +1,9 @@\n {\n   \"name\": \"intellij-styled-search\",\n   \"displayName\": \"IntelliJ Styled Search\",\n   \"description\": \"IntelliJ IDEA style project search — peek-like movable panel with workspace file results\",\n-  \"version\": \"0.1.688\",\n+  \"version\": \"0.1.689\",\n   \"publisher\": \"newdlops\",\n   \"license\": \"MIT\",\n   \"icon\": \"resources/icon.png\",\n   \"repository\": {\n"
                },
                {
                    "date": 1778066911036,
                    "content": "Index: \n===================================================================\n--- \n+++ \n@@ -1,9 +1,9 @@\n {\n   \"name\": \"intellij-styled-search\",\n   \"displayName\": \"IntelliJ Styled Search\",\n   \"description\": \"IntelliJ IDEA style project search — peek-like movable panel with workspace file results\",\n-  \"version\": \"0.1.689\",\n+  \"version\": \"0.1.690\",\n   \"publisher\": \"newdlops\",\n   \"license\": \"MIT\",\n   \"icon\": \"resources/icon.png\",\n   \"repository\": {\n@@ -300,8 +300,13 @@\n           \"type\": \"boolean\",\n           \"default\": false,\n           \"description\": \"Watch external filesystem delete events for zoekt incremental updates. Disabled by default so the extension does not subscribe to every workspace file event; saved editor documents and VS Code delete/rename operations are still tracked.\"\n         },\n+        \"intellijStyledSearch.zoektWatchExternalFileChanges\": {\n+          \"type\": \"boolean\",\n+          \"default\": true,\n+          \"description\": \"Watch external filesystem create/change events for zoekt incremental updates. Enabled by default so MCP and search results see files modified by external agents without falling back to a full workspace scan.\"\n+        },\n         \"intellijStyledSearch.zoektUpdateDebounceMs\": {\n           \"type\": \"number\",\n           \"default\": 5000,\n           \"minimum\": 250,\n@@ -398,8 +403,17 @@\n           \"type\": \"boolean\",\n           \"default\": false,\n           \"description\": \"Watch external filesystem create/change/delete events for call graph incremental updates. Disabled by default so call graph updates only follow confirmed VS Code save/create/delete/rename operations.\"\n         },\n+        \"intellijStyledSearch.callGraphBackend\": {\n+          \"type\": \"string\",\n+          \"enum\": [\n+            \"rust-native\",\n+            \"javascript\"\n+          ],\n+          \"default\": \"rust-native\",\n+          \"description\": \"Backend used for call graph rebuilds. rust-native stores the primary graph in the zoekt-rs index for low-token MCP lookups; javascript materializes the legacy full JS snapshot and is mainly used for semantic parity tests.\"\n+        },\n         \"intellijStyledSearch.callGraphConcurrency\": {\n           \"type\": \"number\",\n           \"default\": 64,\n           \"minimum\": 0,\n"
                },
                {
                    "date": 1778068415515,
                    "content": "Index: \n===================================================================\n--- \n+++ \n@@ -1,9 +1,9 @@\n {\n   \"name\": \"intellij-styled-search\",\n   \"displayName\": \"IntelliJ Styled Search\",\n   \"description\": \"IntelliJ IDEA style project search — peek-like movable panel with workspace file results\",\n-  \"version\": \"0.1.690\",\n+  \"version\": \"0.1.691\",\n   \"publisher\": \"newdlops\",\n   \"license\": \"MIT\",\n   \"icon\": \"resources/icon.png\",\n   \"repository\": {\n"
                },
                {
                    "date": 1778073322915,
                    "content": "Index: \n===================================================================\n--- \n+++ \n@@ -1,9 +1,9 @@\n {\n   \"name\": \"intellij-styled-search\",\n   \"displayName\": \"IntelliJ Styled Search\",\n   \"description\": \"IntelliJ IDEA style project search — peek-like movable panel with workspace file results\",\n-  \"version\": \"0.1.691\",\n+  \"version\": \"0.1.692\",\n   \"publisher\": \"newdlops\",\n   \"license\": \"MIT\",\n   \"icon\": \"resources/icon.png\",\n   \"repository\": {\n"
                },
                {
                    "date": 1778083393468,
                    "content": "Index: \n===================================================================\n--- \n+++ \n@@ -1,9 +1,9 @@\n {\n   \"name\": \"intellij-styled-search\",\n   \"displayName\": \"IntelliJ Styled Search\",\n   \"description\": \"IntelliJ IDEA style project search — peek-like movable panel with workspace file results\",\n-  \"version\": \"0.1.692\",\n+  \"version\": \"0.1.693\",\n   \"publisher\": \"newdlops\",\n   \"license\": \"MIT\",\n   \"icon\": \"resources/icon.png\",\n   \"repository\": {\n"
                },
                {
                    "date": 1778086741197,
                    "content": "Index: \n===================================================================\n--- \n+++ \n@@ -1,9 +1,9 @@\n {\n   \"name\": \"intellij-styled-search\",\n   \"displayName\": \"IntelliJ Styled Search\",\n   \"description\": \"IntelliJ IDEA style project search — peek-like movable panel with workspace file results\",\n-  \"version\": \"0.1.693\",\n+  \"version\": \"0.1.694\",\n   \"publisher\": \"newdlops\",\n   \"license\": \"MIT\",\n   \"icon\": \"resources/icon.png\",\n   \"repository\": {\n"
                },
                {
                    "date": 1778115405709,
                    "content": "Index: \n===================================================================\n--- \n+++ \n@@ -1,9 +1,9 @@\n {\n   \"name\": \"intellij-styled-search\",\n   \"displayName\": \"IntelliJ Styled Search\",\n   \"description\": \"IntelliJ IDEA style project search — peek-like movable panel with workspace file results\",\n-  \"version\": \"0.1.694\",\n+  \"version\": \"0.1.695\",\n   \"publisher\": \"newdlops\",\n   \"license\": \"MIT\",\n   \"icon\": \"resources/icon.png\",\n   \"repository\": {\n"
                },
                {
                    "date": 1778117779351,
                    "content": "Index: \n===================================================================\n--- \n+++ \n@@ -1,9 +1,9 @@\n {\n   \"name\": \"intellij-styled-search\",\n   \"displayName\": \"IntelliJ Styled Search\",\n   \"description\": \"IntelliJ IDEA style project search — peek-like movable panel with workspace file results\",\n-  \"version\": \"0.1.695\",\n+  \"version\": \"0.1.696\",\n   \"publisher\": \"newdlops\",\n   \"license\": \"MIT\",\n   \"icon\": \"resources/icon.png\",\n   \"repository\": {\n"
                },
                {
                    "date": 1778121062571,
                    "content": "Index: \n===================================================================\n--- \n+++ \n@@ -1,9 +1,9 @@\n {\n   \"name\": \"intellij-styled-search\",\n   \"displayName\": \"IntelliJ Styled Search\",\n   \"description\": \"IntelliJ IDEA style project search — peek-like movable panel with workspace file results\",\n-  \"version\": \"0.1.696\",\n+  \"version\": \"0.1.697\",\n   \"publisher\": \"newdlops\",\n   \"license\": \"MIT\",\n   \"icon\": \"resources/icon.png\",\n   \"repository\": {\n"
                },
                {
                    "date": 1778286032472,
                    "content": "Index: \n===================================================================\n--- \n+++ \n@@ -1,9 +1,9 @@\n {\n   \"name\": \"intellij-styled-search\",\n   \"displayName\": \"IntelliJ Styled Search\",\n   \"description\": \"IntelliJ IDEA style project search — peek-like movable panel with workspace file results\",\n-  \"version\": \"0.1.697\",\n+  \"version\": \"0.1.698\",\n   \"publisher\": \"newdlops\",\n   \"license\": \"MIT\",\n   \"icon\": \"resources/icon.png\",\n   \"repository\": {\n"
                },
                {
                    "date": 1778333177455,
                    "content": "Index: \n===================================================================\n--- \n+++ \n@@ -1,9 +1,9 @@\n {\n   \"name\": \"intellij-styled-search\",\n   \"displayName\": \"IntelliJ Styled Search\",\n   \"description\": \"IntelliJ IDEA style project search — peek-like movable panel with workspace file results\",\n-  \"version\": \"0.1.698\",\n+  \"version\": \"0.1.6990\",\n   \"publisher\": \"newdlops\",\n   \"license\": \"MIT\",\n   \"icon\": \"resources/icon.png\",\n   \"repository\": {\n"
                },
                {
                    "date": 1778666751058,
                    "content": "Index: \n===================================================================\n--- \n+++ \n@@ -1,9 +1,9 @@\n {\n   \"name\": \"intellij-styled-search\",\n   \"displayName\": \"IntelliJ Styled Search\",\n   \"description\": \"IntelliJ IDEA style project search — peek-like movable panel with workspace file results\",\n-  \"version\": \"0.1.6990\",\n+  \"version\": \"0.1.7\",\n   \"publisher\": \"newdlops\",\n   \"license\": \"MIT\",\n   \"icon\": \"resources/icon.png\",\n   \"repository\": {\n@@ -37,105 +37,25 @@\n   \"contributes\": {\n     \"commands\": [\n       {\n         \"command\": \"intellijStyledSearch.searchInProject\",\n-        \"title\": \"Find in Path (IntelliJ Style)\",\n+        \"title\": \"Search\",\n         \"category\": \"IntelliJ Search\"\n       },\n       {\n-        \"command\": \"intellijStyledSearch.searchSelection\",\n-        \"title\": \"Find Selection in Project\",\n-        \"category\": \"IntelliJ Search\"\n-      },\n-      {\n-        \"command\": \"intellijStyledSearch.reinject\",\n-        \"title\": \"Reinject Renderer Patch (Uses CDP)\",\n-        \"category\": \"IntelliJ Search\"\n-      },\n-      {\n-        \"command\": \"intellijStyledSearch.stopMonacoCapture\",\n-        \"title\": \"Stop Monaco Capture (Safe)\",\n-        \"category\": \"IntelliJ Search\"\n-      },\n-      {\n-        \"command\": \"intellijStyledSearch.recoverRendererUi\",\n-        \"title\": \"Recover VS Code UI Responsiveness (Safe)\",\n-        \"category\": \"IntelliJ Search\"\n-      },\n-      {\n         \"command\": \"intellijStyledSearch.rebuildIndex\",\n-        \"title\": \"Rebuild Search Index\",\n+        \"title\": \"Force Rebuild Search + Graph Index\",\n         \"category\": \"IntelliJ Search\"\n       },\n       {\n-        \"command\": \"intellijStyledSearch.switchEngine\",\n-        \"title\": \"Switch Search Engine\",\n+        \"command\": \"intellijStyledSearch.diagnosePreviewIntellisense\",\n+        \"title\": \"Diagnose Preview Intellisense (probe Pylance for last previewed URI)\",\n         \"category\": \"IntelliJ Search\"\n-      },\n-      {\n-        \"command\": \"intellijStyledSearch.showZoektInfo\",\n-        \"title\": \"Show Zoekt Diagnostics\",\n-        \"category\": \"IntelliJ Search\"\n-      },\n-      {\n-        \"command\": \"intellijStyledSearch.explainZoektQuery\",\n-        \"title\": \"Explain Query With Zoekt\",\n-        \"category\": \"IntelliJ Search\"\n-      },\n-      {\n-        \"command\": \"intellijStyledSearch.diagnoseFileInIndex\",\n-        \"title\": \"Diagnose Active File in Search Index\",\n-        \"category\": \"IntelliJ Search\"\n-      },\n-      {\n-        \"command\": \"intellijStyledSearch.rebuildCallGraph\",\n-        \"title\": \"Rebuild Call Graph\",\n-        \"category\": \"IntelliJ Search\"\n-      },\n-      {\n-        \"command\": \"intellijStyledSearch.forceRebuildCallGraph\",\n-        \"title\": \"Force Rebuild Call Graph\",\n-        \"category\": \"IntelliJ Search\"\n-      },\n-      {\n-        \"command\": \"intellijStyledSearch.showCallGraphInfo\",\n-        \"title\": \"Show Call Graph Info\",\n-        \"category\": \"IntelliJ Search\"\n-      },\n-      {\n-        \"command\": \"intellijStyledSearch.findCallers\",\n-        \"title\": \"Find Callers\",\n-        \"category\": \"IntelliJ Search\"\n-      },\n-      {\n-        \"command\": \"intellijStyledSearch.findCallees\",\n-        \"title\": \"Find Callees\",\n-        \"category\": \"IntelliJ Search\"\n-      },\n-      {\n-        \"command\": \"intellijStyledSearch.findImplementations\",\n-        \"title\": \"Find Implementations\",\n-        \"category\": \"IntelliJ Search\"\n-      },\n-      {\n-        \"command\": \"intellijStyledSearch.findUsages\",\n-        \"title\": \"Find Usages\",\n-        \"category\": \"IntelliJ Search\"\n-      },\n-      {\n-        \"command\": \"intellijStyledSearch.startMcpServer\",\n-        \"title\": \"Start Codeidx MCP Server\",\n-        \"category\": \"IntelliJ Search\"\n-      },\n-      {\n-        \"command\": \"intellijStyledSearch.stopMcpServer\",\n-        \"title\": \"Stop Codeidx MCP Server\",\n-        \"category\": \"IntelliJ Search\"\n       }\n     ],\n     \"keybindings\": [\n       {\n-        \"command\": \"intellijStyledSearch.searchSelection\",\n+        \"command\": \"intellijStyledSearch.searchInProject\",\n         \"key\": \"ctrl+shift+alt+f\",\n         \"mac\": \"cmd+shift+alt+f\",\n         \"when\": \"editorTextFocus\"\n       },\n@@ -156,88 +76,18 @@\n         {\n           \"submenu\": \"intellijStyledSearch.editorContext\",\n           \"when\": \"editorTextFocus\",\n           \"group\": \"navigation@98\"\n-        },\n-        {\n-          \"command\": \"intellijStyledSearch.searchSelection\",\n-          \"when\": \"editorHasSelection\",\n-          \"group\": \"navigation@99\"\n         }\n       ],\n       \"intellijStyledSearch.editorContext\": [\n         {\n           \"command\": \"intellijStyledSearch.searchInProject\",\n           \"group\": \"1_search@1\"\n         },\n         {\n-          \"command\": \"intellijStyledSearch.searchSelection\",\n-          \"when\": \"editorHasSelection\",\n+          \"command\": \"intellijStyledSearch.rebuildIndex\",\n           \"group\": \"1_search@2\"\n-        },\n-        {\n-          \"command\": \"intellijStyledSearch.findCallees\",\n-          \"group\": \"2_callGraph@2\"\n-        },\n-        {\n-          \"command\": \"intellijStyledSearch.findImplementations\",\n-          \"group\": \"2_callGraph@3\"\n-        },\n-        {\n-          \"command\": \"intellijStyledSearch.findUsages\",\n-          \"group\": \"2_callGraph@4\"\n-        },\n-        {\n-          \"command\": \"intellijStyledSearch.rebuildCallGraph\",\n-          \"group\": \"2_callGraph@5\"\n-        },\n-        {\n-          \"command\": \"intellijStyledSearch.forceRebuildCallGraph\",\n-          \"group\": \"2_callGraph@6\"\n-        },\n-        {\n-          \"command\": \"intellijStyledSearch.showCallGraphInfo\",\n-          \"group\": \"2_callGraph@7\"\n-        },\n-        {\n-          \"command\": \"intellijStyledSearch.startMcpServer\",\n-          \"group\": \"3_mcp@1\"\n-        },\n-        {\n-          \"command\": \"intellijStyledSearch.stopMcpServer\",\n-          \"group\": \"3_mcp@2\"\n-        },\n-        {\n-          \"command\": \"intellijStyledSearch.rebuildIndex\",\n-          \"group\": \"4_index@1\"\n-        },\n-        {\n-          \"command\": \"intellijStyledSearch.switchEngine\",\n-          \"group\": \"4_index@2\"\n-        },\n-        {\n-          \"command\": \"intellijStyledSearch.showZoektInfo\",\n-          \"group\": \"4_index@3\"\n-        },\n-        {\n-          \"command\": \"intellijStyledSearch.explainZoektQuery\",\n-          \"group\": \"4_index@4\"\n-        },\n-        {\n-          \"command\": \"intellijStyledSearch.diagnoseFileInIndex\",\n-          \"group\": \"4_index@5\"\n-        },\n-        {\n-          \"command\": \"intellijStyledSearch.reinject\",\n-          \"group\": \"5_recovery@1\"\n-        },\n-        {\n-          \"command\": \"intellijStyledSearch.stopMonacoCapture\",\n-          \"group\": \"5_recovery@2\"\n-        },\n-        {\n-          \"command\": \"intellijStyledSearch.recoverRendererUi\",\n-          \"group\": \"5_recovery@3\"\n         }\n       ]\n     },\n     \"configuration\": {\n@@ -371,8 +221,13 @@\n           \"type\": \"boolean\",\n           \"default\": false,\n           \"description\": \"Fully dispose the injected Search UI renderer patch when the panel is hidden. Disabled by default so direct inlay clicks can reuse the lightweight renderer hook without repeated CDP reinjection.\"\n         },\n+        \"intellijStyledSearch.previewLanguageFeatures\": {\n+          \"type\": \"boolean\",\n+          \"default\": true,\n+          \"description\": \"Enable Pylance/LSP hover, autocomplete, and other language features inside the preview pane. Creates the embed Monaco editor with isSimpleWidget=false. Default ON because captain log analysis proved isSimpleWidget=true silently suppresses Pylance hover. If you see the preview go blank on click (workbench takeover regression), flip this to false.\"\n+        },\n         \"intellijStyledSearch.keepCdpOpenWhileSearchUiVisible\": {\n           \"type\": \"boolean\",\n           \"default\": true,\n           \"description\": \"Keep the CDP bridge open while the Search UI panel is visible. Enabled by default to avoid repeated SIGUSR1/inspector reconnects during typing and incremental searches; cleanup still runs when the panel is hidden.\"\n@@ -499,8 +354,14 @@\n           \"type\": \"boolean\",\n           \"default\": true,\n           \"description\": \"Show call graph relation links as inlay hints next to symbols. By default this surfaces callers, usages, and implementations.\"\n         },\n+        \"intellijStyledSearch.callGraphMaxUsageResults\": {\n+          \"type\": \"number\",\n+          \"default\": 10000,\n+          \"minimum\": 1,\n+          \"description\": \"Maximum number of usage results returned by Find Usages and the call graph inlay click flow. The previous hard cap of 500 truncated heavy callers like model classes; bump this if your repository still hits the new ceiling.\"\n+        },\n         \"intellijStyledSearch.callGraphShowCalleeInlayHints\": {\n           \"type\": \"boolean\",\n           \"default\": false,\n           \"description\": \"Also show callees in call graph inlay hints. Disabled by default because callers and usages are usually more useful for code navigation and agent context.\"\n"
                },
                {
                    "date": 1778667379996,
                    "content": "Index: \n===================================================================\n--- \n+++ \n@@ -1,9 +1,9 @@\n {\n   \"name\": \"intellij-styled-search\",\n   \"displayName\": \"IntelliJ Styled Search\",\n   \"description\": \"IntelliJ IDEA style project search — peek-like movable panel with workspace file results\",\n-  \"version\": \"0.1.7\",\n+  \"version\": \"0.1.701\",\n   \"publisher\": \"newdlops\",\n   \"license\": \"MIT\",\n   \"icon\": \"resources/icon.png\",\n   \"repository\": {\n@@ -49,8 +49,23 @@\n       {\n         \"command\": \"intellijStyledSearch.diagnosePreviewIntellisense\",\n         \"title\": \"Diagnose Preview Intellisense (probe Pylance for last previewed URI)\",\n         \"category\": \"IntelliJ Search\"\n+      },\n+      {\n+        \"command\": \"intellijStyledSearch.startMcpServer\",\n+        \"title\": \"Start Codeidx MCP Server\",\n+        \"category\": \"IntelliJ Search\"\n+      },\n+      {\n+        \"command\": \"intellijStyledSearch.stopMcpServer\",\n+        \"title\": \"Stop Codeidx MCP Server\",\n+        \"category\": \"IntelliJ Search\"\n+      },\n+      {\n+        \"command\": \"intellijStyledSearch.restartMcpServer\",\n+        \"title\": \"Restart Codeidx MCP Server\",\n+        \"category\": \"IntelliJ Search\"\n       }\n     ],\n     \"keybindings\": [\n       {\n@@ -86,8 +101,20 @@\n         },\n         {\n           \"command\": \"intellijStyledSearch.rebuildIndex\",\n           \"group\": \"1_search@2\"\n+        },\n+        {\n+          \"command\": \"intellijStyledSearch.startMcpServer\",\n+          \"group\": \"2_mcp@1\"\n+        },\n+        {\n+          \"command\": \"intellijStyledSearch.restartMcpServer\",\n+          \"group\": \"2_mcp@2\"\n+        },\n+        {\n+          \"command\": \"intellijStyledSearch.stopMcpServer\",\n+          \"group\": \"2_mcp@3\"\n         }\n       ]\n     },\n     \"configuration\": {\n"
                },
                {
                    "date": 1778752058554,
                    "content": "Index: \n===================================================================\n--- \n+++ \n@@ -1,9 +1,9 @@\n {\n   \"name\": \"intellij-styled-search\",\n   \"displayName\": \"IntelliJ Styled Search\",\n   \"description\": \"IntelliJ IDEA style project search — peek-like movable panel with workspace file results\",\n-  \"version\": \"0.1.701\",\n+  \"version\": \"0.1.703\",\n   \"publisher\": \"newdlops\",\n   \"license\": \"MIT\",\n   \"icon\": \"resources/icon.png\",\n   \"repository\": {\n"
                }
            ],
            "date": 1776584800003,
            "name": "Commit-0",
            "content": "{\n  \"name\": \"intellij-styled-search\",\n  \"displayName\": \"IntelliJ Styled Search\",\n  \"description\": \"IntelliJ IDEA style project search — peek-like movable panel with workspace file results\",\n  \"version\": \"0.0.2\",\n  \"publisher\": \"newdlops\",\n  \"license\": \"MIT\",\n  \"icon\": \"resources/icon.png\",\n  \"repository\": {\n    \"type\": \"git\",\n    \"url\": \"https://github.com/newdlops/intellij-styled-search.git\"\n  },\n  \"bugs\": {\n    \"url\": \"https://github.com/newdlops/intellij-styled-search/issues\"\n  },\n  \"homepage\": \"https://github.com/newdlops/intellij-styled-search#readme\",\n  \"engines\": {\n    \"vscode\": \"^1.75.0\"\n  },\n  \"categories\": [\n    \"Other\"\n  ],\n  \"keywords\": [\n    \"search\",\n    \"find in path\",\n    \"intellij\",\n    \"peek\",\n    \"project search\"\n  ],\n  \"main\": \"./out/extension.js\",\n  \"activationEvents\": [\n    \"onStartupFinished\"\n  ],\n  \"contributes\": {\n    \"commands\": [\n      {\n        \"command\": \"intellijStyledSearch.searchInProject\",\n        \"title\": \"Find in Path (IntelliJ Style)\",\n        \"category\": \"IntelliJ Search\"\n      },\n      {\n        \"command\": \"intellijStyledSearch.searchSelection\",\n        \"title\": \"Find Selection in Project\",\n        \"category\": \"IntelliJ Search\"\n      },\n      {\n        \"command\": \"intellijStyledSearch.reinject\",\n        \"title\": \"Reinject Renderer Patch (Recovery)\",\n        \"category\": \"IntelliJ Search\"\n      },\n      {\n        \"command\": \"intellijStyledSearch.rebuildIndex\",\n        \"title\": \"Rebuild Search Index\",\n        \"category\": \"IntelliJ Search\"\n      },\n      {\n        \"command\": \"intellijStyledSearch.diagnoseFileInIndex\",\n        \"title\": \"Diagnose Active File in Search Index\",\n        \"category\": \"IntelliJ Search\"\n      }\n    ],\n    \"keybindings\": [\n      {\n        \"command\": \"intellijStyledSearch.searchSelection\",\n        \"key\": \"ctrl+shift+alt+f\",\n        \"mac\": \"cmd+shift+alt+f\",\n        \"when\": \"editorTextFocus\"\n      },\n      {\n        \"command\": \"intellijStyledSearch.searchInProject\",\n        \"key\": \"ctrl+shift+alt+p\",\n        \"mac\": \"cmd+shift+alt+p\"\n      }\n    ],\n    \"menus\": {\n      \"editor/context\": [\n        {\n          \"command\": \"intellijStyledSearch.searchSelection\",\n          \"when\": \"editorHasSelection\",\n          \"group\": \"navigation@99\"\n        }\n      ]\n    },\n    \"configuration\": {\n      \"title\": \"IntelliJ Styled Search\",\n      \"properties\": {\n        \"intellijStyledSearch.excludeGlobs\": {\n          \"type\": \"array\",\n          \"default\": [\n            \"**/node_modules/**\",\n            \"**/.git/**\",\n            \"**/out/**\",\n            \"**/dist/**\",\n            \"**/build/**\",\n            \"**/.next/**\",\n            \"**/coverage/**\"\n          ],\n          \"description\": \"Glob patterns to exclude from search.\"\n        },\n        \"intellijStyledSearch.maxFileSize\": {\n          \"type\": \"number\",\n          \"default\": 1048576,\n          \"description\": \"Maximum file size (bytes) to include in search.\"\n        },\n        \"intellijStyledSearch.maxResults\": {\n          \"type\": \"number\",\n          \"default\": 2000,\n          \"description\": \"Maximum number of match lines to return.\"\n        }\n      }\n    }\n  },\n  \"scripts\": {\n    \"bundle:monaco\": \"node scripts/bundleMonaco.js\",\n    \"compile\": \"npm run bundle:monaco && tsc -p ./\",\n    \"watch\": \"tsc -watch -p ./\",\n    \"vscode:prepublish\": \"npm run compile\",\n    \"pretest\": \"npm run compile\",\n    \"test\": \"vscode-test\"\n  },\n  \"devDependencies\": {\n    \"@types/glob\": \"^8.1.0\",\n    \"@types/mocha\": \"^10.0.6\",\n    \"@types/node\": \"^18.0.0\",\n    \"@types/vscode\": \"^1.75.0\",\n    \"@types/ws\": \"^8.5.10\",\n    \"@vscode/test-cli\": \"^0.0.10\",\n    \"@vscode/test-electron\": \"^2.4.1\",\n    \"esbuild\": \"^0.21.0\",\n    \"glob\": \"^8.1.0\",\n    \"mocha\": \"^10.2.0\",\n    \"monaco-editor\": \"^0.52.0\",\n    \"typescript\": \"^5.0.0\"\n  },\n  \"dependencies\": {\n    \"ws\": \"^8.18.0\"\n  }\n}\n"
        }
    ]
}